fastfargate/__init__.py
fastfargate/py.typed
fastfargate/_jsii/__init__.py
fastfargate/_jsii/fastfargate@0.0.23.jsii.tgz
fastfargate-0.0.23.dist-info/LICENSE
fastfargate-0.0.23.dist-info/METADATA
fastfargate-0.0.23.dist-info/WHEEL
fastfargate-0.0.23.dist-info/top_level.txt
fastfargate-0.0.23.dist-info/RECORD
