Metadata-Version: 2.1
Name: fastfargate
Version: 0.0.23
Summary: This package is for Projen Demo
Home-page: https://github.com/AymanZahran/projen-cdk-tutorial-part-1.git
Author: Ayman Zahran<ah.zahran@outlook.com>
License: Apache-2.0
Project-URL: Source, https://github.com/AymanZahran/projen-cdk-tutorial-part-1.git
Platform: UNKNOWN
Classifier: Intended Audience :: Developers
Classifier: Operating System :: OS Independent
Classifier: Programming Language :: JavaScript
Classifier: Programming Language :: Python :: 3 :: Only
Classifier: Programming Language :: Python :: 3.6
Classifier: Programming Language :: Python :: 3.7
Classifier: Programming Language :: Python :: 3.8
Classifier: Programming Language :: Python :: 3.9
Classifier: Typing :: Typed
Classifier: Development Status :: 5 - Production/Stable
Classifier: License :: OSI Approved
Requires-Python: >=3.6
License-File: LICENSE
Requires-Dist: aws-cdk-lib (<3.0.0,>=2.1.0)
Requires-Dist: constructs (<11.0.0,>=10.0.5)
Requires-Dist: jsii (<2.0.0,>=1.55.1)
Requires-Dist: publication (>=0.0.3)
